{
  "snapshot_at": "2026-05-12T10:25:15+09:00",
  "components": [
    {
      "id": "api",
      "label": "API",
      "status": "down",
      "last_check": "2026-05-12T10:25:15+09:00",
      "latency_ms": 10073
    },
    {
      "id": "mcp",
      "label": "MCP",
      "status": "down",
      "last_check": "2026-05-12T10:25:15+09:00",
      "latency_ms": 10046
    },
    {
      "id": "billing",
      "label": "Billing (Stripe)",
      "status": "ok",
      "last_check": "2026-05-12T10:25:15+09:00",
      "latency_ms": 0
    },
    {
      "id": "data-freshness",
      "label": "データ鮮度",
      "status": "degraded",
      "last_check": "2026-05-12T10:25:15+09:00",
      "latency_ms": 0
    },
    {
      "id": "dashboard",
      "label": "ダッシュボード",
      "status": "degraded",
      "last_check": "2026-05-12T10:25:15+09:00",
      "latency_ms": 282
    }
  ],
  "overall": "down"
}
