[
  {
    "source_url": "https://www.mlit.go.jp/report/press/content/001842304.pdf",
    "publisher_domain": "mlit.go.jp",
    "page_count": 2,
    "text_extractable": true,
    "tables_detected": true,
    "fields_found": [
      "deadline",
      "eligible_applicant",
      "subsidy_rate",
      "max_amount",
      "required_docs",
      "contact"
    ],
    "parser_risk": "low",
    "reason": "2 pages; text layer extractable; tables detected in sampled pages; fields: deadline,eligible_applicant,subsidy_rate,max_amount,required_docs,contact"
  },
  {
    "source_url": "https://www.mlit.go.jp/kankocho/content/001386417.pdf",
    "publisher_domain": "mlit.go.jp",
    "page_count": 15,
    "text_extractable": true,
    "tables_detected": true,
    "fields_found": [
      "deadline",
      "eligible_applicant",
      "subsidy_rate",
      "max_amount",
      "required_docs",
      "contact"
    ],
    "parser_risk": "low",
    "reason": "15 pages; text layer extractable; tables detected in sampled pages; fields: deadline,eligible_applicant,subsidy_rate,max_amount,required_docs,contact"
  },
  {
    "source_url": "https://www.mhlw.go.jp/content/11600000/001239692.pdf",
    "publisher_domain": "mhlw.go.jp",
    "page_count": 18,
    "text_extractable": true,
    "tables_detected": true,
    "fields_found": [
      "deadline",
      "max_amount",
      "required_docs",
      "contact",
      "update_date"
    ],
    "parser_risk": "medium",
    "reason": "18 pages; text layer extractable; tables detected in sampled pages; fields: deadline,max_amount,required_docs,contact,update_date"
  },
  {
    "source_url": "https://www.mhlw.go.jp/content/001520023.pdf",
    "publisher_domain": "mhlw.go.jp",
    "page_count": 2,
    "text_extractable": true,
    "tables_detected": false,
    "fields_found": [
      "max_amount"
    ],
    "parser_risk": "high",
    "reason": "2 pages; text layer extractable; no tables detected in first sampled pages; fields: max_amount"
  }
]
